PythonPlug/__init__.py
PythonPlug/adapter.py
PythonPlug/conn.py
PythonPlug/contrib/__init__.py
PythonPlug/contrib/parser/json_parser.py
PythonPlug/contrib/plug/guard_plug.py
PythonPlug/contrib/plug/router_plug.py
PythonPlug/exception.py
PythonPlug/plug.py
PythonPlug/typing.py
PythonPlug/utils/__init__.py
PythonPlug/utils/conn.py
pythonplug-0.1.2.dist-info/LICENSE.md
pythonplug-0.1.2.dist-info/WHEEL
pythonplug-0.1.2.dist-info/METADATA
pythonplug-0.1.2.dist-info/RECORD
